README
setup.py
pipimport/__init__.py
pipimport.egg-info/PKG-INFO
pipimport.egg-info/SOURCES.txt
pipimport.egg-info/dependency_links.txt
pipimport.egg-info/top_level.txt