Metadata-Version: 1.1
Name: pipimport
Version: 0.2.3
Summary: Automatically install missing modules using pip at import time. Best used with virtualenv.
Home-page: https://github.com/chaosct/pipimport
Author: Carles F. Julia
Author-email: carles@fjulia.name
License: MIT
Keywords: pip virtualenv import hook
Platform: UNKNOWN
Classifier: Development Status :: 3 - Alpha
Classifier: Topic :: Software Development :: Libraries
Classifier: Topic :: System :: Software Distribution
Classifier: License :: OSI Approved :: MIT License
